setup.cfg
setup.py
osimis_file_helpers/__init__.py
osimis_file_helpers/fileHelpers.py
osimis_file_helpers.egg-info/PKG-INFO
osimis_file_helpers.egg-info/SOURCES.txt
osimis_file_helpers.egg-info/dependency_links.txt
osimis_file_helpers.egg-info/top_level.txt