Metadata-Version: 1.0
Name: osimis-file-helpers
Version: 0.1.0
Summary: A set of utilities to perform file operations
Home-page: https://bitbucket.org/osimis/python-osimis-file-helpers
Author: Alain Mazy
Author-email: am@osimis.io
License: UNKNOWN
Keywords: Helpers,File
Platform: UNKNOWN
